{
  "intents": {
    "smalltalk": [
      "can we talk",
      "i'm bored",
      "i am bored",
      "let's chat",
      "talk to me",
      "have a conversation",
      "small talk",
      "chat with me",
      "i want to talk",
      "start talking",
      "begin conversation"
    ],
    "journaling": [
      "journal entry",
      "start journaling",
      "begin journal",
      "write journal",
      "journal session",
      "log my thoughts",
      "record my day",
      "daily journal",
      "journaling time",
      "write down my thoughts"
    ],
    "meditation": [
      "meditation session",
      "begin meditation",
      "start meditating",
      "meditation time",
      "guided meditation",
      "mindfulness session",
      "calm my mind",
      "meditation practice",
      "relaxation session",
      "meditation"
    ],
    "quote": [
      "quote of the day",
      "daily quote",
      "inspirational quote",
      "motivational quote",
      "give me a quote",
      "share a quote",
      "wisdom quote",
      "quote please",
      "inspire me",
      "motivate me"
    ],
    "gratitude": [
      "gratitude practice",
      "gratitude session",
      "practice gratitude",
      "grateful thoughts",
      "thankful practice",
      "gratitude exercise",
      "count blessings",
      "gratitude journal",
      "appreciation practice",
      "gratitude time"
    ],
    "termination": [
      "goodbye",
      "bye",
      "see you later",
      "talk to you later",
      "that's all",
      "end conversation",
      "stop talking",
      "finish",
      "done",
      "exit",
      "quit",
      "stop",
      "end",
      "close"
    ]
  },
  "smalltalk": {
    "system_prompt": "You are Well-Bot,a friendly emotional wellness assistant having a small talk with your user. Keep your responses casual, short and concise. Do not use emojis. Here is what the user said:",
    "termination_phrases": [
      "Okay, bye",
      "I have to go now",
      "Talk later",
      "Stop talking",
      "Exit"
    ],
    "prompts": {
      "start": "What's on your mind?",
      "nudge": "Hey are you still there? Feel free to continue our conversation.",
      "timeout": "It seems like you're not there. I'll go take a break now. Just call me when you're ready to talk again.",
      "end": "Okay talk later, bye for now!."
    }
  },
  "journal": {
    "termination_phrases": [
      "stop journal",
      "save journal",
      "end entry",
      "that's all",
      "finish journal",
      "done journaling",
      "end journal",
      "stop recording"
    ],
    "prompts": {
      "start": "Ready to journal. Start speaking after the tone. You can pause anytime to think. Say 'stop journal' when you're finished.",
      "nudge": "Are you still there? Continue speaking or say 'stop journal' to finish.",
      "saving": "Saving your journal entry now.",
      "saved": "Journal entry saved with {word_count} words.",
      "timeout": "Saving your journal entry now."
    }
  },
  "wakeword_responses": {
    "prompts": {
      "wakeword_detected": "Hey, I heard you called me. What can I help you with?",
      "nudge": "I'm listening. What would you like to do?",
      "timeout": "I'll be here when you need me. Just say my name.",
      "unknown_intent": "I didn't quite catch that. Could you please repeat?",
      "activity_unavailable": "That feature isn't available yet. What else can I help you with?"
    }
  },
  "audio_paths": {
    "wokeword_audio_path": "assets/ENGLISH/wokeword_EN_male.wav",
    "start_smalltalk_audio_path": "assets/ENGLISH/start_smalltalk_EN_male.wav",
    "start_journal_audio_path": "assets/ENGLISH/start_journal_EN_male.wav",
    "start_gratitude_audio_path": "assets/ENGLISH/start_gratitude_EN_male.wav",
    "start_meditation_audio_path": "assets/ENGLISH/start_meditation_EN_male.wav",
    "start__quote_audio_path": "assets/ENGLISH/start_quote_EN_male.wav",
    "nudge_audio_path": "assets/ENGLISH/inactivity_nudge_EN_male.wav",
    "termination_audio_path": "assets/ENGLISH/termination_EN_male.wav",
    "end_audio_path": "assets/ENGLISH/end_smalltalk_EN_male.wav",
    "prompt_repeat_path": "assets/ENGLISH/prompt_repeat_EN_male.wav",
    "activity_unavailable_path": "assets/ENGLISH/activity_unavailable_EN_male.wav"
  }
}

